{
  "questions": [
    {
      "question": "1",
      "type": "single",
      "content": "关于信息的描述，不正确的是（）。",
      "options": [
        "A.信息不是物质，也不是能量，它以一种普遍形式，表达物质运动规律，在客观世界中大量存在、产生和传递",
        "B.信息是用来消除随机不定性的东西",
        "C.信息的特征主要包括客观性、普遍性、无限性、动态性、相对性、依附性、变换性、传递性、层次性、系统性和转化性",
        "D.对于经济与社会信息而言，其最重要的特性是安全性"
      ],
      "answer": "D",
      "explanation": "P2，对于金融信息而言，其最重要的特性是安全性；而对于经济与社会信息而言，其最重要的特性是及时性。",
      "difficulty": 2,
      "tags": [
        "第01章-信息化发展"
      ]
    },
    {
      "question": "2",
      "type": "single",
      "content": "下列说法正确的是（）。",
      "options": [
        "A.信息只存在家庭中",
        "B.信息只存在图书馆中",
        "C.信息只存在校园里",
        "D.信息无处不在"
      ],
      "answer": "D",
      "explanation": "P2，信息不是物质，也不是能量，它以一种普遍形式，表达物质运动规律，在客观世界中大量存在、产生和传递。",
      "difficulty": 1,
      "tags": [
        "第01章-信息化发展"
      ]
    },
    {
      "question": "3",
      "type": "single",
      "content": "信息的基础是（）。",
      "options": [
        "A.数据",
        "B.知识",
        "C.事实",
        "D.概念"
      ],
      "answer": "A",
      "explanation": "信息的基础是数据。",
      "difficulty": 1,
      "tags": [
        "第01章-信息化发展"
      ]
    },
    {
      "question": "4",
      "type": "single",
      "content": "下列说法正确的是（）。",
      "options": [
        "A.信息是指音讯、消息、信息系统传输和处理的对象，泛指人类社会传播的一切内容",
        "B.信息是物质、能量及其属性的标示的集合，是确定性的减少",
        "C.信息是物质，也不是能力，它以一种普遍形式，表达物质运动规律，在客观世界中大量存在、产生和传递",
        "D.香农指出：“信息是用来消除随机的东西”"
      ],
      "answer": "A",
      "explanation": "P1-2，信息是物质、能量及其属性的标示的集合，是确定性的增加，所有B错误。  \n信息不是物质，也不是能力，它以一种普遍形式，表达物质运动规律，在客观世界中大量存在、产生和传递，所有C错误。\n\n香农指出：“信息是用来消除随机不定性的东西”，所有D错误。",
      "difficulty": 2,
      "tags": [
        "第01章-信息化发展"
      ]
    },
    {
      "question": "5",
      "type": "single",
      "content": "下列说法种不正确的是（）。",
      "options": [
        "A.信息的目的是用来“消除不确定的因素”",
        "B.信息具有价值，而价值的大小决定于信息的数量",
        "C.信息系统是由相互联系、相互依赖、相互作用的事物或过程组成的具有整体功能和综合行为的统一体",
        "D.简单地说，信息系统就是通过输入数据，然后进行加工处理，最后产生信息的系统"
      ],
      "answer": "B",
      "explanation": "P1-3，信息具有价值，而价值的大小决定于信息的质量",
      "difficulty": 2,
      "tags": [
        "第01章-信息化发展"
      ]
    },
    {
      "question": "6",
      "type": "single",
      "content": "信息系统就是通过输入数据，然后进行加工处理，最后产生信息的系统。（）和（）是信息系统的显著特点。",
      "options": [
        "A.面向目标；支持管理",
        "B.面向管理；支持发展",
        "C.面向管理；支持生产",
        "D.面向目标；支持生产"
      ],
      "answer": "C",
      "explanation": "P3, 信息系统就是通过输入数据，然后进行加工处理，最后产生信息的系统。面向管理和支持生产是信息系统的显著特点。",
      "difficulty": 2,
      "tags": [
        "第01章-信息化发展"
      ]
    },
    {
      "question": "7",
      "type": "single",
      "content": "信息系统的生命周期可以简化为：系统规划、系统分析、系统设计、系统实施、系统运行和维护等阶段，其中与系统实施对应的是（）。",
      "options": [
        "A.项目开发计划",
        "B.需求分析",
        "C.详细设计",
        "D.编码、测试"
      ],
      "answer": "D",
      "explanation": "P4，信息系统的生命周期可以简化为：系统规划（可行性分析与项目开发计划），系统分析（需求分析），系统设计（概要设计、详细设计），系统实施（编码、测试），系统运行和维护等阶段。",
      "difficulty": 2,
      "tags": [
        "第01章-信息化发展"
      ]
    },
    {
      "question": "44",
      "type": "single",
      "content": "数据仓库是一个面向主题的、集成的、相对稳定的、反映历史变化的数据集合，用于支持管理决策，其系统结构如下图所示：图中①应为（）。\n\n${images/909c1f56d7d2117316d5d97a0ff576c139cf8d320652e1114e3ce90a77de33f0.jpg}",
      "options": [
        "A.中心数据服务器",
        "B.OLTP服务器",
        "C.OLAP服务器",
        "D.决策应用服务器"
      ],
      "answer": "C",
      "explanation": "P47,\n\n${images/ce4de732109ab9da0bc34a144a5519bcbd34adeb3276b5cdea48eac9b1e2f040.jpg}  \n图2-2 数据仓库体系结构",
      "difficulty": 1,
      "tags": [
        "第02章-信息技术发展"
      ]
    }
  ]
}